django_autotag-0.1.4.dist-info/METADATA
django_autotag-0.1.4.dist-info/metadata.json
django_autotag-0.1.4.dist-info/DESCRIPTION.rst
django_autotag-0.1.4.dist-info/pbr.json
django_autotag-0.1.4.dist-info/top_level.txt
django_autotag-0.1.4.dist-info/RECORD
django_autotag-0.1.4.dist-info/WHEEL
autotag_app/views.py
autotag_app/utils.py
autotag_app/admin.py
autotag_app/__init__.py
autotag_app/autotag.py
autotag_app/stopwords.py
autotag_app/models.py
autotag_app/tests.py
